LICENSE
MANIFEST.in
README.txt
setup.py
upload.bat
radware_os_lb_v1_kilo/__init__.py
radware_os_lb_v1_kilo/exceptions.py
radware_os_lb_v1_kilo/rest_client.py
radware_os_lb_v1_kilo/v1_driver.py
radware_os_lb_v1_kilo.egg-info/PKG-INFO
radware_os_lb_v1_kilo.egg-info/SOURCES.txt
radware_os_lb_v1_kilo.egg-info/dependency_links.txt
radware_os_lb_v1_kilo.egg-info/not-zip-safe
radware_os_lb_v1_kilo.egg-info/top_level.txt