Metadata-Version: 1.1
Name: radware-os-lb-v1-kilo
Version: 4.0.0-1
Summary: Radware NG driver for Openstack KILO LBaaS v1
Home-page: https://pypi.python.org/pypi/radware_os_lb_v1_kilo
Author: Evgeny Fedoruk, Radware
Author-email: evgenyf@radware.com
License: UNKNOWN
Keywords: openstack,radware,lbaasv2
Platform: UNKNOWN
Classifier: Environment :: OpenStack
Classifier: Intended Audience :: Information Technology
Classifier: Intended Audience :: System Administrators
Classifier: License :: OSI Approved :: Apache Software License
Classifier: Operating System :: POSIX :: Linux
Classifier: Programming Language :: Python :: 2.7
